[
  {
    "id": 17900200250256908,
    "created_at": 1636791509,
    "text": "❤️",
    "owner": {
      "id": "Wj-Qk9LlLflM-FmtD5I69Q==",
      "username": "1lt-oMtaYd1VQeyDUGKWMQ=="
    },
    "likes_count": 0,
    "answers": []
  },
  {
    "id": 17916398231082785,
    "created_at": 1636630241,
    "text": "😔😔😔",
    "owner": {
      "id": "s9zVdqIw023Z7SosDAFAcQ==",
      "username": "N0UZRKk0VCC6tezSfM5NOw=="
    },
    "likes_count": 0,
    "answers": []
  },
  {
    "id": 17900437028362810,
    "created_at": 1636618101,
    "text": "Ich war ja skeptisch wg dem Projekt. Aber bisher, woow, Respekt.",
    "owner": {
      "id": "VaanAaA2DgeSDXnC1abA4A==",
      "username": "9gcmr8Dhdq2exSohWKMuDg=="
    },
    "likes_count": 1,
    "answers": []
  },
  {
    "id": 17914643606111498,
    "created_at": 1636615543,
    "text": "❤️",
    "owner": {
      "id": "w-88t3P9s6co6Bu7LQ0yfg==",
      "username": "cBT6Z1Pa_MJWQGJJIckIXA=="
    },
    "likes_count": 0,
    "answers": []
  },
  {
    "id": 17898334346501202,
    "created_at": 1636578426,
    "text": "😢",
    "owner": {
      "id": "advM_vw_cdhRJ1dS3QfGDA==",
      "username": "uPYWBRsWTlPKoMV1WgzXqA=="
    },
    "likes_count": 0,
    "answers": []
  },
  {
    "id": 18242245522075570,
    "created_at": 1636574035,
    "text": "❤️❤️❤️❤️",
    "owner": {
      "id": "9FuY_1pnj4x_kFdWhyY5jA==",
      "username": "w4VqUB9Yxd0FBqX1bc7qJg=="
    },
    "likes_count": 0,
    "answers": []
  },
  {
    "id": 17924574184937142,
    "created_at": 1636563066,
    "text": "Unvorstellbar, wie schlimm das alles gewesen sein muss😢",
    "owner": {
      "id": "632ajT_v0q_9OPd6h-tBGA==",
      "username": "_c01PKWANfqDHoEqmHkp4A=="
    },
    "likes_count": 0,
    "answers": []
  },
  {
    "id": 17887949744439678,
    "created_at": 1636562411,
    "text": "Ich war gestern mit meinen Kindern Stolpersteine putzen. Meine älteste ist 8 und schon gut „kindgerecht* aufgeklärt, was das anbelangt. Es ist so wichtig das das niemals in Vergessenheit gerät.",
    "owner": {
      "id": "d0w0W7s1qBLX1ddZD0Ws0g==",
      "username": "xjZgw4mQ_SsTFJSWQVQi8g=="
    },
    "likes_count": 1,
    "answers": []
  },
  {
    "id": 18006360283367950,
    "created_at": 1636550597,
    "text": "🙌",
    "owner": {
      "id": "VTTUMAWV-HeMVnnrnMuZdw==",
      "username": "IwvAm4WLCDn_y2bBjvk3gg=="
    },
    "likes_count": 0,
    "answers": []
  },
  {
    "id": 17888462048422749,
    "created_at": 1636541469,
    "text": "Sophie du hast SO recht !",
    "owner": {
      "id": "nGsizKD6vZWBKz8a4frsCQ==",
      "username": "dXWfttF-Vm9PpUpYlqpbZA=="
    },
    "likes_count": 0,
    "answers": []
  },
  {
    "id": 17882261435496401,
    "created_at": 1636538382,
    "text": "#nazisrausausdenparlamenten #keinenmillimeternachrechts #noafd #niewieder #keinvergessen 🕯🕊",
    "owner": {
      "id": "MWcrtZmbw-9GodNOdfVS5w==",
      "username": "zZrvCH5sii-e-3Pskvgskg=="
    },
    "likes_count": 1,
    "answers": []
  },
  {
    "id": 17908706483285003,
    "created_at": 1636536475,
    "text": "❤️🔥",
    "owner": {
      "id": "ns0fA-6iWpjtfwF2ad10SQ==",
      "username": "J-TokTCUVhmw-GRHzm9ntw=="
    },
    "likes_count": 1,
    "answers": []
  },
  {
    "id": 18259590241043639,
    "created_at": 1636534337,
    "text": "Es ist Gut, wenn gerade Jüngere diese paranoide Staatsinszenierung so eindringlich wahrnehmen können. Aber darüber nicht vergessen, dieser Antisemitismus wurde auch nach dem Ende der faschistischen Ära latent und bewusst geduldet und nicht verfolgt! Siehe Horror KZ Arzt Mengele z.B. Dieser Vergessensvirus lebt noch heute! Auch nach Hanau. Drum sind solche geschichtlichen, authentischen Repliken Gold wert.",
    "owner": {
      "id": "ccvymf_cGuDiK1khrV993A==",
      "username": "8XdSleqqO4at_GyeT86rtA=="
    },
    "likes_count": 0,
    "answers": []
  },
  {
    "id": 17899869095259516,
    "created_at": 1636533444,
    "text": "Ich schäme mich für die Leute die dabei zugesehen und auch noch geklatscht haben!",
    "owner": {
      "id": "G9GO2JdcuLL_7o3u6xR5XA==",
      "username": "GxdViKGIs0l4mGC_levqOQ=="
    },
    "likes_count": 0,
    "answers": []
  },
  {
    "id": 17896845917509650,
    "created_at": 1636532035,
    "text": "#TeamSoffer Die heutige Pandemie-Situation mit der Hitler-Diktatur zu vergleichen ist nicht angebracht. Solche Aussagen widersprechen nicht nur jeglichen Fakten, sondern sind außerdem respektlos gegenüber den unzähligen Opfern der damaligen Zeit. Wir behalten uns daher vor, entsprechende Kommentare zu entfernen.",
    "owner": {
      "id": "9rICyTfoSV8xPafAZ0Xo0w==",
      "username": "hib4mKmHA-vgwtwb0Q_04A=="
    },
    "likes_count": 338,
    "answers": [
      {
        "id": 17901290570474845,
        "created_at": 1636568849,
        "text": "@hib4mKmHA-vgwtwb0Q_04A== 👏",
        "owner": {
          "id": "-Q69vPc2L8t0AVKipUf-5g==",
          "username": "NvekJNMRf_q-kvEpkjS6JA=="
        },
        "likes_count": 0
      }
    ]
  },
  {
    "id": 17941575121629106,
    "created_at": 1636529370,
    "text": "Leider war mein Heimatland, Estland, offiziell judenfrei. Glückligerweise haben einige Juden/Jüdinnen diese Katastrophe übergelebt. Leider gab es sicherlich weniger als 10 Überlebender.",
    "owner": {
      "id": "6dhi4sbb7Yhk3d61II2eAQ==",
      "username": "nXpX9edA-LSTh_ohCAdG_Q=="
    },
    "likes_count": 0,
    "answers": []
  },
  {
    "id": 17857700684623366,
    "created_at": 1636526048,
    "text": "🖤",
    "owner": {
      "id": "n4wUnTgwCZuaafWtks0kjQ==",
      "username": "rR_oZ6XVIb2wMcCJdxLxBA=="
    },
    "likes_count": 0,
    "answers": []
  },
  {
    "id": 17915547578101264,
    "created_at": 1636525930,
    "text": "Wusste man damals, dass Deutschland den krieg begonnen hatte? Oder war es mehr eine Vermutung bzw ein offenes Geheimnis?",
    "owner": {
      "id": "-KjbyzmovetsVx8nJa6sjA==",
      "username": "ZQOd4k4lRkYSV9w6wkq0RA=="
    },
    "likes_count": 0,
    "answers": []
  },
  {
    "id": 18100344196272960,
    "created_at": 1636520066,
    "text": "Ich kenn das als Reichskristallnacht warum heist es nun progrome",
    "owner": {
      "id": "EKdvAusqbUeDrcYEo_eRog==",
      "username": "kfTErw-8Kym7wpnrXkoGjQ=="
    },
    "likes_count": 0,
    "answers": [
      {
        "id": 18262871050053888,
        "created_at": 1636529742,
        "text": "@kfTErw-8Kym7wpnrXkoGjQ== weil das Wort Kristall das Geschehen einfach komplett verharmlost. Ein Kristall ist was schönes, glitzerndes, gläsernes. Dadurch wird eine Verknüpfung zu den fallenden Kronleuchtern und herumliegenden Glasscherben suggeriert und damit oft nur noch an zerstörte Gebäude gedacht und ausgeblendet, dass in der Nacht auch ca 1.500 Menschen getötet wurden.",
        "owner": {
          "id": "E0R-9vBPDF-nz4YLj3PEeA==",
          "username": "QC1Z7LpiYihPHCZObuIQhA=="
        },
        "likes_count": 2
      }
    ]
  },
  {
    "id": 18179495995196660,
    "created_at": 1636518523,
    "text": "🐞",
    "owner": {
      "id": "hLK1CRVBQcYCNkIeu685xQ==",
      "username": "jT9OVWBJOYaX4Zsg_NcVzQ=="
    },
    "likes_count": 0,
    "answers": []
  },
  {
    "id": 17883962045530477,
    "created_at": 1636517674,
    "text": "Es ist erschreckend. Bei uns stand auch eine Synagoge. Während ringsherum alles schon am 9.11. brannte, wehrten sich die Feuerwehr und die Bürger, sodass die Synagoge erst einen Tag später brannte. Diese Menschen sind genauso Menschen wie wir und haben eine Würde, die es zu beschützen gilt!",
    "owner": {
      "id": "2DERs_NoArSc4qkYg5d6SQ==",
      "username": "XSBIc6Cb_zmVslIHHQ0yPQ=="
    },
    "likes_count": 0,
    "answers": []
  },
  {
    "id": 17909117792313827,
    "created_at": 1636514721,
    "text": "Ich bin heute bei Dunkelheit durch die Hauptstraße unserer Altstadt gefahren. An jedem Stolperstein brannte eine Kerze. Es waren viele Kerzen, für so eine kleine Stadt.",
    "owner": {
      "id": "FfbIb_UBpulCAbyEwq891w==",
      "username": "LVsVpMgnttj0mdF_LAFtNw=="
    },
    "likes_count": 1,
    "answers": []
  },
  {
    "id": 17977532323440194,
    "created_at": 1636506621,
    "text": "#ichbinsophiescholl wir hätten mehr Heldinnen wie dich gebraucht! Danke das du so gekämpft hast.",
    "owner": {
      "id": "2Dc24K1LuAnf8RDms4iACQ==",
      "username": "riEWBZ02Lw55MYVhy0ba4Q=="
    },
    "likes_count": 1,
    "answers": []
  },
  {
    "id": 18069180016293522,
    "created_at": 1636502106,
    "text": "Mein Gott hat übrigens eine jüdische Mutter. Das sagt für mich eigentlich alles zum Thema Antisemitismus!",
    "owner": {
      "id": "W2WjfnB-fuvAmVldKFobHA==",
      "username": "PHzf68YhoOfgIkPlfUV6Zg=="
    },
    "likes_count": 0,
    "answers": []
  },
  {
    "id": 17924624275909027,
    "created_at": 1636498860,
    "text": "😢",
    "owner": {
      "id": "obb3q6If8-LgsIE1GN7F9Q==",
      "username": "go9xqklAxvTDCi8Tpri5Sg=="
    },
    "likes_count": 0,
    "answers": []
  },
  {
    "id": 18142594354224434,
    "created_at": 1636498759,
    "text": "Heute ist hier in Wien ein Denkmal enthüllt worden, auf dem die Namen aller jüdischen Bewohner Wiens, die verschleppt und ermordet wurden, eingraviert sind . Initiiert von einem Überlebenden dieser Nacht . Es ist sehr berührend, diese vielen Namen zu lesen .",
    "owner": {
      "id": "gOzliD2NcpyVww0MUKQVKQ==",
      "username": "3bCl48b6O2XhCV-AMPFK3A=="
    },
    "likes_count": 10,
    "answers": [
      {
        "id": 18136586593237873,
        "created_at": 1636536552,
        "text": "@3bCl48b6O2XhCV-AMPFK3A== wo?",
        "owner": {
          "id": "ApzsosSyYc-0KYS8X6RHhA==",
          "username": "VIu-3v08IC4qDhG8KnX5Wg=="
        },
        "likes_count": 0
      },
      {
        "id": 17938355905684195,
        "created_at": 1636830671,
        "text": "@VIu-3v08IC4qDhG8KnX5Wg== Es steht auf einer Grünfläche vor der Nationalbank im 9. Bezirk, Ostarrichipark, nahe dem alten AKH !",
        "owner": {
          "id": "gOzliD2NcpyVww0MUKQVKQ==",
          "username": "3bCl48b6O2XhCV-AMPFK3A=="
        },
        "likes_count": 0
      },
      {
        "id": 17891621939377683,
        "created_at": 1636837887,
        "text": "@3bCl48b6O2XhCV-AMPFK3A== danke",
        "owner": {
          "id": "ApzsosSyYc-0KYS8X6RHhA==",
          "username": "VIu-3v08IC4qDhG8KnX5Wg=="
        },
        "likes_count": 0
      }
    ]
  },
  {
    "id": 17938039804707167,
    "created_at": 1636495984,
    "text": "😯😞😡",
    "owner": {
      "id": "E2uHH1Oexehymgcs8aMvHA==",
      "username": "xNVUAx0aja_zTl_Xa_28Sg=="
    },
    "likes_count": 0,
    "answers": []
  },
  {
    "id": 17843622593685275,
    "created_at": 1636495522,
    "text": "@hib4mKmHA-vgwtwb0Q_04A== aber es gab doch den Überfall auf den Sender Gleiwitz?",
    "owner": {
      "id": "L7n7k8dIGgWUxNn5i1D96w==",
      "username": "tfLAExu-VUXZPZowZBbTYA=="
    },
    "likes_count": 0,
    "answers": []
  },
  {
    "id": 17898343895301927,
    "created_at": 1636495469,
    "text": "😢😢😢",
    "owner": {
      "id": "A-eHqpu82Ds1KV76-592IA==",
      "username": "ZfTx5EU45NnB0AX5Eg0kvQ=="
    },
    "likes_count": 1,
    "answers": []
  },
  {
    "id": 17878335803565239,
    "created_at": 1636493263,
    "text": "Und leider ist erst in diesem Sommer, im Juni, ein Brandanschlag auf die neu aufgebaute Synagoge in Ulm verübt worden. Der Täter ist immer noch nicht gefasst. Antisemitismus ist weiter ein Problem bei uns und wir dürfen die Augen nicht davor verschließen.",
    "owner": {
      "id": "tHhsBln1Eg07izmyBHwkfg==",
      "username": "nDED6rWXM5XQlTK5S5OFXw=="
    },
    "likes_count": 4,
    "answers": []
  },
  {
    "id": 18151880803207734,
    "created_at": 1636493239,
    "text": "Wir werden immer weiter erinnern!",
    "owner": {
      "id": "lCpp_fhSSCgpjyUtjCLTSQ==",
      "username": "yRxQg5dChQjjjkN1YN0meg=="
    },
    "likes_count": 0,
    "answers": []
  },
  {
    "id": 17989953322397966,
    "created_at": 1636493178,
    "text": "💔😢",
    "owner": {
      "id": "d_0TZSDZ0B0nwOpQDl5TNg==",
      "username": "R3zLtYusg1Tb7GkHvoLGZg=="
    },
    "likes_count": 0,
    "answers": []
  },
  {
    "id": 18152934505168339,
    "created_at": 1636492940,
    "text": "Hatten denn die Bürger bis zum Ende des Krieges wirklich keine Ahnung was mit den Millionen von juden passiert ist? Ich kann mir das immer ga nicht vorstellen, das muss doch irgendwie nach außen getragen worden sein 🤔",
    "owner": {
      "id": "TG6vl_2h2-jleHNnAK6sNw==",
      "username": "YS-nO4He-QSqtT4GZuVfmg=="
    },
    "likes_count": 0,
    "answers": [
      {
        "id": 18252982627070730,
        "created_at": 1636494241,
        "text": "@YS-nO4He-QSqtT4GZuVfmg== noch dazu: die Konzentrationslager wurden auch gar nicht „versteckt“, dass es sie gab, wusste man. Und was passierte wurde auch weitergetragen. Fritz, Sophies Freund, hat ihr z.B. im Sommer 1942 in einem Brief geschrieben: „Es ist erschreckend mit welcher zynischen Kaltschnäuzigkeit mein Kommandeur von der Abschlachtung sämtlicher (im Original unterstrichen) Juden des besetzten Rußland erzählt hat.“",
        "owner": {
          "id": "3W3u797RFAMi2jy9PWfsyw==",
          "username": "rWW9geJBzAUmEVaqJ6ihiQ=="
        },
        "likes_count": 3
      },
      {
        "id": 17957215732524751,
        "created_at": 1636570710,
        "text": "@YS-nO4He-QSqtT4GZuVfmg==  hitlers willige vollstrecker von daniel goldhagen  gibt da gute antworten drauf",
        "owner": {
          "id": "j-prBgqQ-inuxsMIn0FgTw==",
          "username": "tHorC-WtFdBMNQnMzeGxjg=="
        },
        "likes_count": 0
      },
      {
        "id": 17938180789689315,
        "created_at": 1636624301,
        "text": "@YS-nO4He-QSqtT4GZuVfmg== #TeamSoffer Die Kenntnisse der Deutschen vom Holcoaust und dem systematischen Mord an Jüd:innen waren länger umstritten, jedoch spielt diese Aussage in das revisionistische Narrativ der “ahnungslosen Deutschen” hinein. Stattdessen belegen Untersuchungen, dass die Deutschen eine Menge über die Machenschaften des NS-Regimes wussten und natürlich auch darin involviert waren. Die Konzentrationslager und andere Vernichtungslager waren oft in und an Städten gelegen, deren Bewohner:innen die Lager und auch die Geschehnisse dort mitbekommen haben. Zudem wurden in Tageszeitungen etc. eine Vielzahl an Berichten über die KZs veröffentlicht, die auch in Teilen der deutschen Bevölkerung damals Anklang fanden.\nWeitere Infos zu diesem Thema findest du zum Beispiel im Bericht \"Holocaust - Die Lüge von den ahnungslosen Deutschen\" bei Panorama (ARD).",
        "owner": {
          "id": "9rICyTfoSV8xPafAZ0Xo0w==",
          "username": "hib4mKmHA-vgwtwb0Q_04A=="
        },
        "likes_count": 0
      },
      {
        "id": 17918181982946584,
        "created_at": 1636494065,
        "text": "@YS-nO4He-QSqtT4GZuVfmg== doch viele wussten das. @ichbinsophiescholl sagt heute in ihrer Story ja selbst, dass man es wissen kann, wenn man es will.",
        "owner": {
          "id": "3W3u797RFAMi2jy9PWfsyw==",
          "username": "rWW9geJBzAUmEVaqJ6ihiQ=="
        },
        "likes_count": 4
      }
    ]
  },
  {
    "id": 17902316222208460,
    "created_at": 1636492479,
    "text": "Diese Schande wird unser Land auf ewig begleiten.",
    "owner": {
      "id": "X21cEdO8LHyqIrpiy2M8iQ==",
      "username": "wwzvo9LiGXSud-xvYd318Q=="
    },
    "likes_count": 1,
    "answers": []
  },
  {
    "id": 17925366862833104,
    "created_at": 1636492360,
    "text": "Wenn es einen Gott gibt,muss er mich um Verzeihung bitten .\n(Geschrieben an einer Mauer von Auschwitz )  vergesst es nie. Nie!!!",
    "owner": {
      "id": "80sphCfdTIk1kVJG_31rYA==",
      "username": "FRN7eSY2xWDb6n2ihfUBiQ=="
    },
    "likes_count": 0,
    "answers": []
  },
  {
    "id": 17876713916592961,
    "created_at": 1636492335,
    "text": "Erinnerungen aufrecht erhalten.  Auch wenn die heutige Generation nichts dafür kann,  Sie können helfen, dass es in Ihrer Zukunft nicht in Vergessenheit gerät!❤️",
    "owner": {
      "id": "q5ySxH4maE0NmBtHpbVF9w==",
      "username": "gRFmFxe4hBhV-DbnKS7-Fg=="
    },
    "likes_count": 2,
    "answers": []
  },
  {
    "id": 17920438840997492,
    "created_at": 1636492250,
    "text": "😔🙏",
    "owner": {
      "id": "Ao5MfkC0d7uwsKtOqJinhg==",
      "username": "qp5UmhBXsfbkcKud3StGWQ=="
    },
    "likes_count": 0,
    "answers": []
  },
  {
    "id": 17906701286266157,
    "created_at": 1636491781,
    "text": "😢",
    "owner": {
      "id": "f6XszD_FjtpY6mWuiouG4g==",
      "username": "eOpfLwqlBcTF6E5SHyaXog=="
    },
    "likes_count": 0,
    "answers": []
  },
  {
    "id": 17899929311263356,
    "created_at": 1636491091,
    "text": "Direkt in meiner Nachbarschaft sind auch 4 Personen deportiert worden. Jeden Tag komme ich an dem Haus vorbei, jeden Tag habe ich die Bilder vor Augen, obwohl ich sie gar nicht selbst gesehen habe. Wie gut, dass es Menschen gibt, die den Widerstand wagen",
    "owner": {
      "id": "vURGFIYFpJmgF9iQ0S2AlQ==",
      "username": "j1OphD1XZ8j0UYmQujZwwA=="
    },
    "likes_count": 1,
    "answers": []
  },
  {
    "id": 17963620732495191,
    "created_at": 1636490602,
    "text": "Ich finde es gut, dass das Thema auf diesem Kanal thematisiert wird! Auch wenn die Reichsprogromnacht 4 Jahre vorher stattfand",
    "owner": {
      "id": "mWZU7KckVv8Nalp--f4fpw==",
      "username": "s39TnB_sF6uzwQdMNBcuSQ=="
    },
    "likes_count": 0,
    "answers": [
      {
        "id": 18010571614356658,
        "created_at": 1636492991,
        "text": "@BBb9c9N186Y6LPWa8LOvjA== ja ich weiß. Aber sonst erzählt \"Sophie\" ja in der Regel, was gerade passiert, also im Jahr 1942 😀",
        "owner": {
          "id": "mWZU7KckVv8Nalp--f4fpw==",
          "username": "s39TnB_sF6uzwQdMNBcuSQ=="
        },
        "likes_count": 0
      },
      {
        "id": 17949874375570820,
        "created_at": 1636529815,
        "text": "@s39TnB_sF6uzwQdMNBcuSQ== mag dieses Mal aber daran liegen, dass sich dieses schreckliche Ereignis jährt.",
        "owner": {
          "id": "X--fB3Vikq8SC0YN5aywdw==",
          "username": "BBb9c9N186Y6LPWa8LOvjA=="
        },
        "likes_count": 1
      },
      {
        "id": 17909341508287193,
        "created_at": 1636492743,
        "text": "@s39TnB_sF6uzwQdMNBcuSQ== davon ist hier in der Erzählung ja auch die Rede😀",
        "owner": {
          "id": "X--fB3Vikq8SC0YN5aywdw==",
          "username": "BBb9c9N186Y6LPWa8LOvjA=="
        },
        "likes_count": 1
      }
    ]
  },
  {
    "id": 18262949764002813,
    "created_at": 1636489790,
    "text": "Unvorstellbares Leid 🖤 und unvorstellbare Taten 😭",
    "owner": {
      "id": "0SFehl8fe81gJ-hI1YROeA==",
      "username": "BonULF-Ra2l8JcVhy2wdRg=="
    },
    "likes_count": 2,
    "answers": []
  },
  {
    "id": 17862838511603854,
    "created_at": 1636488921,
    "text": "💔",
    "owner": {
      "id": "iCXWQXgrWv_t7cbZ1WqQIQ==",
      "username": "-NY2KtOUfMWgGyuGzXqrdQ=="
    },
    "likes_count": 0,
    "answers": []
  },
  {
    "id": 17918547860066325,
    "created_at": 1636488860,
    "text": "😢",
    "owner": {
      "id": "w71rMxAnVAyjvVTcLAS-1A==",
      "username": "Y0uodCDSk8-WZT9LFuFAGQ=="
    },
    "likes_count": 0,
    "answers": []
  },
  {
    "id": 17858369555620171,
    "created_at": 1636488821,
    "text": "😔🖤",
    "owner": {
      "id": "lsPDhuiDf_2ovipCRkvbMg==",
      "username": "g2j48mxiC-pXdhM-t8PpfA=="
    },
    "likes_count": 0,
    "answers": []
  },
  {
    "id": 17917605035062281,
    "created_at": 1636488420,
    "text": "Ich denke an die weißen Rosen. Kämpft weiter! Ihr schafft das!",
    "owner": {
      "id": "nVANPIqa1wH_bPyEPC9C9A==",
      "username": "d14wTqfkOx2u8LeAs4Fo_w=="
    },
    "likes_count": 3,
    "answers": []
  },
  {
    "id": 17931792934839376,
    "created_at": 1636487858,
    "text": "Und immer noch gibt es Holocaust Leugner in jeder Altersgruppe 😢",
    "owner": {
      "id": "zYgW8zKffRoSN4yWRYMJsw==",
      "username": "IMqtxdKycfU-JEn_mK-jFg=="
    },
    "likes_count": 3,
    "answers": []
  },
  {
    "id": 18010177393334340,
    "created_at": 1636487837,
    "text": "Ich war heute auf einer Gedenkveranstaltung dazu. Danke für eure Arbeit hier, dass ihr uns die hässliche Fratze des Faschismus und Nationalsozoalismus zeigt. Wir wollen nie wieder zurück.",
    "owner": {
      "id": "lYui8GPI0J2wyeL05qCbjw==",
      "username": "IZIH2Sx5ShLbfJfw6D7_rA=="
    },
    "likes_count": 0,
    "answers": []
  },
  {
    "id": 17899977806267018,
    "created_at": 1636487785,
    "text": "Das darf nie vergessen werden, aber es darf auch nie wieder passieren",
    "owner": {
      "id": "ZjfgIRah0DB1q4yUXbeQ9g==",
      "username": "QYzTxa70QpgstpM7avOElA=="
    },
    "likes_count": 10,
    "answers": []
  },
  {
    "id": 17928653020877309,
    "created_at": 1636487688,
    "text": "Einer der dunkelsten Momente in unserer Geschichte und es wird noch Schlimmer. Was würden wir heute machen, wenn Synagogen brennen oder Moscheen???",
    "owner": {
      "id": "9ghBkFSYZvwW62PNrXXEtA==",
      "username": "Qwc5sz6EZ1mRvqr_mcE1NQ=="
    },
    "likes_count": 1,
    "answers": [
      {
        "id": 17910675197068741,
        "created_at": 1636501260,
        "text": "@Qwc5sz6EZ1mRvqr_mcE1NQ== Es brennen heute Synagogen! Zumindest gibt es Anschläge auf Synagogen. Fenster gehen nur nicht zu Bruch, weil sie aus Panzerglas sind!",
        "owner": {
          "id": "4Ko8vbOLC9g6FCrEKGtRbw==",
          "username": "H7KmzuTymVSSnFVg4fW_Aw=="
        },
        "likes_count": 2
      }
    ]
  },
  {
    "id": 17909223722077790,
    "created_at": 1636487565,
    "text": "🖤",
    "owner": {
      "id": "oCDBumdGnehbS734nSWGGA==",
      "username": "fOcRmr3zVJbe_iPEpaLjmw=="
    },
    "likes_count": 1,
    "answers": []
  },
  {
    "id": 17978447683437979,
    "created_at": 1636486916,
    "text": "Was damals passiert ist ist unbeschreiblich 😶...es liegt an uns allen, dass so etwas nie wieder passiert. ❤️",
    "owner": {
      "id": "ZwqaJ8La5YXinl3nXw4heg==",
      "username": "BRJQAjU1ggaPv20QfX38Ng=="
    },
    "likes_count": 14,
    "answers": []
  },
  {
    "id": 17953566670545169,
    "created_at": 1636486653,
    "text": "Sowas muss man in Erinnerung behalten damit dies nie wieder passiert",
    "owner": {
      "id": "3gmukvbdSXdjWyZz0SwSaw==",
      "username": "sZbA9eAeNIWsN3dQy1fDTQ=="
    },
    "likes_count": 4,
    "answers": [
      {
        "id": 18025471483322468,
        "created_at": 1636486921,
        "text": "@sZbA9eAeNIWsN3dQy1fDTQ== Da stimme ich dir aus vollem Herzen zu!",
        "owner": {
          "id": "9rICyTfoSV8xPafAZ0Xo0w==",
          "username": "hib4mKmHA-vgwtwb0Q_04A=="
        },
        "likes_count": 8
      },
      {
        "id": 17934664411757459,
        "created_at": 1636486963,
        "text": "@hib4mKmHA-vgwtwb0Q_04A== mega das du dich so dafür einsetzt obwohl es sehr gefährlich enden könnte . Du bist so ein Vorbild",
        "owner": {
          "id": "3gmukvbdSXdjWyZz0SwSaw==",
          "username": "sZbA9eAeNIWsN3dQy1fDTQ=="
        },
        "likes_count": 1
      }
    ]
  },
  {
    "id": 17933383561812611,
    "created_at": 1636486624,
    "text": "Niemals wieder :-( Niemals vergessen 🖤🖤🖤",
    "owner": {
      "id": "Q7-i0rgZWLEw5Ts2YWmbuw==",
      "username": "QFgrYjQEG6LeYI0db4jLxQ=="
    },
    "likes_count": 1,
    "answers": []
  },
  {
    "id": 18102189973272010,
    "created_at": 1636486300,
    "text": "😥",
    "owner": {
      "id": "m9Xz-8Genr83KWzVvV8D4Q==",
      "username": "SRUV3LxgTpxAH96O_q2Jmg=="
    },
    "likes_count": 1,
    "answers": []
  },
  {
    "id": 17933491846705746,
    "created_at": 1636486039,
    "text": "😢😢😢",
    "owner": {
      "id": "k1IzTxVXjUB8oTEULQWmoQ==",
      "username": "q5F7-yZt-8SJr6MKV0hkMQ=="
    },
    "likes_count": 2,
    "answers": []
  },
  {
    "id": 17912423396132803,
    "created_at": 1636485968,
    "text": "😢",
    "owner": {
      "id": "BmFSfyV6dbmcj0m5WeZUQw==",
      "username": "wmzQeZW5WLJByWKUBLRLcg=="
    },
    "likes_count": 1,
    "answers": []
  },
  {
    "id": 17933499085774284,
    "created_at": 1636485876,
    "text": "Danke für die tolle Arbeit die ihr hier rein steckt! Fürs wach rütteln, zurück holen der Erinnernungen, aufmerksam machen etc. Ich bin heute mal wieder über einige Stolpersteine 'gestolpert' und es ist erschreckend wie viele es in meiner kleinen Stadt überall verteilt gibt.",
    "owner": {
      "id": "_RsmlbxBJ9VIL9US85btsg==",
      "username": "eB23MKZzaZAtwapsXOTXwQ=="
    },
    "likes_count": 2,
    "answers": []
  },
  {
    "id": 17901042128352259,
    "created_at": 1636485758,
    "text": "In Lübeck hab ich in einer der sieben Kirchen eine Ausstellung besuchen dürfen, die sich malerisch mit zerstörten Synagogen beschäftigt hatte. War sehr gut.",
    "owner": {
      "id": "ho0AZMfBCMinRTwu37DrTQ==",
      "username": "e5IPpvARKOSuDanpe2wFFg=="
    },
    "likes_count": 0,
    "answers": []
  },
  {
    "id": 17974940452446342,
    "created_at": 1636485753,
    "text": "Ich kann einfach nicht glauben, das meine Oma zu dieser Zeit gelebt hat. Ich kenne alle ihre Geschichten vom Krieg aber immer wenn ich Bilder oder Filme sehe, wird mir die Realität des erzählten klar. Das ganze ist nicht ausgedacht oder 500 Jahre her, das ganze war so nah bei uns. Ich verstehe nicht wieso nicht mehr Leute Ehrfurcht haben und erst recht nicht wie Menschen das gut finden können was damals passiert ist.",
    "owner": {
      "id": "QqzhnZSm0GCckMDHgFRlvQ==",
      "username": "rgH-4RdBlwH06IAs0CWFGw=="
    },
    "likes_count": 45,
    "answers": [
      {
        "id": 18152470057205741,
        "created_at": 1636487118,
        "text": "@rgH-4RdBlwH06IAs0CWFGw== #TeamSoffer Vielen Dank für deinen Kommentar. Es freut uns, wenn wir mit diesem Projekt zu persönlichen Bezügen anregen können. Viele Grüße!",
        "owner": {
          "id": "9rICyTfoSV8xPafAZ0Xo0w==",
          "username": "hib4mKmHA-vgwtwb0Q_04A=="
        },
        "likes_count": 13
      },
      {
        "id": 17978151556441187,
        "created_at": 1636495489,
        "text": "@rgH-4RdBlwH06IAs0CWFGw== ich stimme dem gänzlich zu. Was unsere Großeltern erlebt haben, ist für mich nicht vorstellbar, was für ein Alltag...",
        "owner": {
          "id": "S_nniaYfEfl7vMgQmfFjIA==",
          "username": "qRcQzD7CqsLudqTYCYMdKw=="
        },
        "likes_count": 2
      },
      {
        "id": 17925107209827373,
        "created_at": 1636493435,
        "text": "@rgH-4RdBlwH06IAs0CWFGw== ich kann es auch nicht verstehen, was in den Köpfen dieser Menschen abgeht. Ich hatte auch das Glück eine Zeitzeugin als Oma gehabt zu haben. Habe bis letztes Jahr immer wieder mit ihr über die Ereignisse sprechen können und kann mir trotzdem nicht ansatzweise ausmalen wie schlimm ihre Jugend für sie gewesen sein muss. Aber sie hat Gott sei Dank überlebt 👼🏼 jetzt liegt es an uns, dass sich diese Zeit niemals wiederholt. Am Tage der Progromnacht war sie 11 Jahre Alt, alt genug um es mitzubekommen, zu jung um etwas wirkliches dagegen zu unternehmen.",
        "owner": {
          "id": "YwDhT155hmOmKUdY3v79NQ==",
          "username": "SpW-qi4NOvCXUpXL2JO1NA=="
        },
        "likes_count": 3
      },
      {
        "id": 17904586247168716,
        "created_at": 1636527185,
        "text": "@rgH-4RdBlwH06IAs0CWFGw== meine Oma und mein Opa kamen beide aus der Ecke Ulm und Umgebung, ich selbst war oft genug dort und man realisiert das oft gar nicht so, dass es eigentlich noch nicht mal 100 Jahre her ist. Es ist irgendwie so fern und doch so unfassbar nah, gruselig irgendwie und man kann nur hoffen das es sowas nie wieder geben wird.",
        "owner": {
          "id": "K0ixznKA25B_Yn6wQ-8NgA==",
          "username": "Q-cXenehgzt2qR-7mwfraA=="
        },
        "likes_count": 1
      },
      {
        "id": 17854063973656924,
        "created_at": 1636528799,
        "text": "@rgH-4RdBlwH06IAs0CWFGw== meine Großeltern wollten nie mit mir über diese Zeit reden. Mein Opa hatte sich are Verletzungen vom Krieg, aber wir haben nie ein Wort verloren darüber",
        "owner": {
          "id": "CJZIRFq2cQN8iD8xVKpFBw==",
          "username": "ee786yAWqQf8Q65XK9Ww4g=="
        },
        "likes_count": 0
      }
    ]
  },
  {
    "id": 17843041799687275,
    "created_at": 1636485679,
    "text": "😢😢😢",
    "owner": {
      "id": "lUhUArXjDP5ZA7y1GnrKeQ==",
      "username": "vGWYo4eOpIVroqbjvM-88w=="
    },
    "likes_count": 3,
    "answers": []
  },
  {
    "id": 18264257326049678,
    "created_at": 1636485367,
    "text": "Auf der Seite der bpb.de gibt es unter \"Die inszenierte Empörung - Der 9. November 1938\" eine mehrteilige pdf-Reihe mit ganz vielen Materialien/Dokumente aus der Zeit:\nz. B. Tagebucheinträge,den Bericht eines SA-Mannes, Berichte von Diplomaten in ihre Heimatländer, der Predigt eines Pfarrers aus Oberlenningen in Baden-Württemberg und auch die genauesten Presseanweisungen aus dem \"Reichspropagandaministerium\"wie über die Geschehnisse berichtet werden sollte.",
    "owner": {
      "id": "WCvKFQOJZ9Nps46QU5naiw==",
      "username": "Fy-DLa3DTwl8nhY6R4Sr0A=="
    },
    "likes_count": 19,
    "answers": []
  },
  {
    "id": 17917791433945866,
    "created_at": 1636485316,
    "text": "❤🖤 Der Aufbau einer neuen Welt des Friedens und der Freiheit ist unser Ziel.  Das sind wir all denen schuldig die ihr Leben lassen mussten.",
    "owner": {
      "id": "1AvNIxeOqzi-QseMGQpAKw==",
      "username": "t1oO0RdWvaQhuYejyYbkJg=="
    },
    "likes_count": 3,
    "answers": []
  },
  {
    "id": 17901117392236982,
    "created_at": 1636485192,
    "text": "Liebe Sophie, leider ist diese Art der Ungerechtigkeit noch lange nicht vorbei. Auch 83jahre später gibt es Menschen, die keinen Respekt vor jüdischem Leben, Schaffen und Kultur haben. Letztes Jahr gab es eine Ausstellung in Bochum über jüdische Sportler. Figuren wurden in der Fußgängerzone der Innenstadt aufgestellt. In der Nacht vom 9. auf den 10.11. ist dann folgendes passiert.: \"  Die Täter haben in der Nacht vom 9. auf den 10. November die lebensgroßen Plexiglasfiguren der Leichtathletin Lilli Hennoch sowie der Turnolympiasieger Alfred und Gustav Felix Flatow zerstört. Bereits in den Wochen zuvor waren die Figur von Walther Bensemann beschädigt und die Stele der Brüder Flatow mit antisemitischen Parolen beschmiert worden. Die Veranstalter haben Anzeige gegen Unbekannt erstattet.\" Quelle: WDR 1, 11.11.2020",
    "owner": {
      "id": "nxp0u4PmInS9xOgZFcWrrA==",
      "username": "CJZBUlaqWllop90-4LO81w=="
    },
    "likes_count": 6,
    "answers": []
  },
  {
    "id": 17963388385496221,
    "created_at": 1636485070,
    "text": "Liken fühlt sich eigentlich sehr falsch an...",
    "owner": {
      "id": "fWvOFQOeQCJGZ031p0KyuQ==",
      "username": "THCkcDPCo7EYjg9UB31Jug=="
    },
    "likes_count": 1,
    "answers": []
  },
  {
    "id": 17880753215551287,
    "created_at": 1636485046,
    "text": "Es darf nie mehr vergessen werden. Auch deshalb, weil vielen Deutschen es „ganz recht“ war, was mit ihren jüdischen Mitbürgern passierte.",
    "owner": {
      "id": "iGc5AL-JYjoFjS3mAkbi2A==",
      "username": "iSNyWeayvFHbX8CfkZvv6A=="
    },
    "likes_count": 26,
    "answers": [
      {
        "id": 17921889880964728,
        "created_at": 1636485601,
        "text": "@iSNyWeayvFHbX8CfkZvv6A== Wir müssen gegen etwas gegen diese Gleichgültigkeit und dieses stillschweigende Dulden unternehmen...",
        "owner": {
          "id": "9rICyTfoSV8xPafAZ0Xo0w==",
          "username": "hib4mKmHA-vgwtwb0Q_04A=="
        },
        "likes_count": 16
      },
      {
        "id": 17891389052378567,
        "created_at": 1636525654,
        "text": "@hib4mKmHA-vgwtwb0Q_04A== dann informiert doch hier und jetzt über jüdische Aktivist*Innen. Oder über Personen und Einrichtungen, die wirklich gute Arbeit gegen Antisemitismus machen. Über gute Accounts, Bücher, Podcasts, Angebote, Vereine, Stiftungen etc.",
        "owner": {
          "id": "M-PYqAZdrra_mvQ2aBZ2lQ==",
          "username": "IKomZ8Py4JqAR0NLUa-dBw=="
        },
        "likes_count": 5
      }
    ]
  },
  {
    "id": 17904601904175959,
    "created_at": 1636484769,
    "text": "🖤",
    "owner": {
      "id": "EDxWfTR9SXUEK5638nF48A==",
      "username": "Eoiz27GCbIRycuK8XUlF7Q=="
    },
    "likes_count": 2,
    "answers": []
  },
  {
    "id": 17863747943632121,
    "created_at": 1636484651,
    "text": "Ich bin auf den Tag genau 40 Jahre später geboren. Der 9.11 ging in vielerlei Hinsicht positiv wie leider auch negativ in die Geschichtsbücher ein. Aber sowas wie 1938 darf niemals wieder passieren.",
    "owner": {
      "id": "r9J3d7g0d8nncxj0yOYv-g==",
      "username": "lGA_qvv_vD0x8R2DUE4LTw=="
    },
    "likes_count": 0,
    "answers": []
  },
  {
    "id": 17952900487520088,
    "created_at": 1636484636,
    "text": "😢",
    "owner": {
      "id": "F8osI6-89Cd4bkKPk1fx2g==",
      "username": "F4q7AV98v_ig52WfJq93BQ=="
    },
    "likes_count": 1,
    "answers": []
  },
  {
    "id": 18113742304250403,
    "created_at": 1636484522,
    "text": "Ich bin sehr gespannt wie die letzten Tage der Scholl Geschwister dargestellt werden. Einerseits warte ich gespannt darauf andererseits will ich auch gar nicht das es geschieht.",
    "owner": {
      "id": "FsWBsJCIVzd4Ehsfnk5DpQ==",
      "username": "8ElEhOtDz9RsNuYCjEJrcA=="
    },
    "likes_count": 11,
    "answers": [
      {
        "id": 17850162179667678,
        "created_at": 1636485159,
        "text": "Die Vorstellung ist einfach nur traurig. Zwei junge, engagierte, starke und mutige Menschen. Die Darstellung hier macht das Ende noch erschreckender, als es ohnehin schon ist.😢 Wenn man heute den Einfluss von rechts so sieht, ist das beängstigend.",
        "owner": {
          "id": "wqR7-dZKMNp4Zqg6CdsDSg==",
          "username": "ixJLO373bkFL83kYK5eTfg=="
        },
        "likes_count": 3
      }
    ]
  },
  {
    "id": 18254172886067544,
    "created_at": 1636484325,
    "text": "😢",
    "owner": {
      "id": "WN-ULr-w5LMCVfc-8EbpDQ==",
      "username": "ja7A98qnwX_yB8an6oVkIw=="
    },
    "likes_count": 2,
    "answers": []
  },
  {
    "id": 17943797008617085,
    "created_at": 1636484323,
    "text": "Heute im jahr 2021 haben wir vor einigen Häusern jener Juden, die Opfer der Nazis wurden sogenannte Stolpersteine im Bordstein angebracht. Auf diesen stehen Name, Geburtstag, Tag der Verschleppung, Todesort und wenn nachvollziehen auch der Tag bzw. Das Jahr. Am heutigen Tag werden diese von Freiwilligen geputzt, Blumen niedergelegt und Kerzen angezündet, um nie zu vergessen.",
    "owner": {
      "id": "W1Uj6T9kcLpXvm97g62ATg==",
      "username": "oZ3VP6HNlJHEhF9nmQILZA=="
    },
    "likes_count": 24,
    "answers": []
  },
  {
    "id": 17864457629631305,
    "created_at": 1636484287,
    "text": "Das Schlimmste Kapitel unserer Nation nahm seinen Lauf danach. 😔Es wird für mich nie nachvollziehbar sein, was die Menschen im Ganzen dazu getrieben hat bzw. sie dabei mitmachen lassen hat.",
    "owner": {
      "id": "Tqu88Min530K7Yyrgz1dkQ==",
      "username": "JqWE3s1N-K-lHRWIDZqNKQ=="
    },
    "likes_count": 10,
    "answers": []
  },
  {
    "id": 17902152671197490,
    "created_at": 1636484287,
    "text": "😢",
    "owner": {
      "id": "1vJHyeAMhQBhH9IyjoN1og==",
      "username": "Fv3YpotXATcoojfy5W6uqg=="
    },
    "likes_count": 2,
    "answers": []
  },
  {
    "id": 17917211978027958,
    "created_at": 1636484187,
    "text": "Sind denn die meisten Synagoge die verbrannt wurden wieder aufgebaut worden?",
    "owner": {
      "id": "_6Wm3tw2WR4UPqLm5rc-rw==",
      "username": "NqSlEKOfZQFRi6x1U5suvw=="
    },
    "likes_count": 1,
    "answers": [
      {
        "id": 18260954293007848,
        "created_at": 1636487569,
        "text": "@DY4Gpi0i9zqPDmvlcB_PPg== #TeamSoffer Sehr gern. Aktuell wird in mehreren Fällen diskutiert, inwiefern Synagogen originalgetreu wiederaufgebaut werden sollen. In München wird nun die von den Pogromen betroffene Synagoge Reichenbachstraße aufwändig saniert. Zur Eröffnung soll dann alles so aussehen wie zur damaligen Eröffnung 1931. Mehr dazu auch in diesem Beitrag des Bayerischen Rundfunks: https://www.youtube.com/watch?v=cazGYTLS07I",
        "owner": {
          "id": "9rICyTfoSV8xPafAZ0Xo0w==",
          "username": "hib4mKmHA-vgwtwb0Q_04A=="
        },
        "likes_count": 26
      },
      {
        "id": 18029291587317028,
        "created_at": 1636486326,
        "text": "@DY4Gpi0i9zqPDmvlcB_PPg== #TeamSoffer Im Fall der Ulmer Synagoge hielten sich die Brandschäden in Grenzen, sodass die Synagoge hätte wieder aufgebaut werden können. Der Oberbürgermeister forderte jedoch den Abbruch, für die die jüdische Gemeinde aufkommen musste.",
        "owner": {
          "id": "9rICyTfoSV8xPafAZ0Xo0w==",
          "username": "hib4mKmHA-vgwtwb0Q_04A=="
        },
        "likes_count": 10
      },
      {
        "id": 17954035465536479,
        "created_at": 1636492960,
        "text": "@GBNuV8-QGX0-C4Ins2QErg== und im Juni wurde ein Brandanschlag auf die neue Synagoge in Ulm verübt. Wir müssen wachsam bleiben und uns gegen Antisemitismus einsetzen.",
        "owner": {
          "id": "tHhsBln1Eg07izmyBHwkfg==",
          "username": "nDED6rWXM5XQlTK5S5OFXw=="
        },
        "likes_count": 4
      },
      {
        "id": 17953405708545972,
        "created_at": 1636526240,
        "text": "@duShmHs3yFqqWu8Eh0tIgA== oh, das war mir nicht bekannt. Du hast recht, das Thema ist immernoch aktuell",
        "owner": {
          "id": "gnFKm1z1tYlGZo5raNmDjw==",
          "username": "GBNuV8-QGX0-C4Ins2QErg=="
        },
        "likes_count": 1
      },
      {
        "id": 17943272725589636,
        "created_at": 1636495738,
        "text": "@hib4mKmHA-vgwtwb0Q_04A==  Ulm hat seit einiger Zeit wieder eine Synagoge. Danke an die die sie aufgebaut haben.",
        "owner": {
          "id": "cRCjRKJEp609DFVF8Mx3sQ==",
          "username": "oa44inBV2DnibNr7WLMGlQ=="
        },
        "likes_count": 0
      },
      {
        "id": 17924364061935713,
        "created_at": 1636486951,
        "text": "@hib4mKmHA-vgwtwb0Q_04A== okay danke fürs aufklären!☺",
        "owner": {
          "id": "_6Wm3tw2WR4UPqLm5rc-rw==",
          "username": "NqSlEKOfZQFRi6x1U5suvw=="
        },
        "likes_count": 2
      },
      {
        "id": 17904107996332843,
        "created_at": 1636488111,
        "text": "@hib4mKmHA-vgwtwb0Q_04A== es gibt jetzt aber eine neue sehr schöne Synagoge dort in Ulm. Die ist vor ein paar Jahren eröffnet worden.",
        "owner": {
          "id": "gnFKm1z1tYlGZo5raNmDjw==",
          "username": "GBNuV8-QGX0-C4Ins2QErg=="
        },
        "likes_count": 2
      }
    ]
  },
  {
    "id": 17849168315670485,
    "created_at": 1636484182,
    "text": "😢😢😢",
    "owner": {
      "id": "_cXJkqbO9pEg7LeS0hye-Q==",
      "username": "lt_v5NdAIPSe9LtcAThcyw=="
    },
    "likes_count": 1,
    "answers": []
  },
  {
    "id": 17852878604659730,
    "created_at": 1636484153,
    "text": "@hib4mKmHA-vgwtwb0Q_04A== Schon mit dem Boykott der jüdischen Geschäfte im April 33 und dem Erlass der Nürnberger Gesetze Ende Sommer 35 war klar dass die Juden gesellschaftlich eliminiert werden sollen... Man wollte bis zum Ausbau der Mordmaschinerie der Vernichtungslager das vertuschen was längst beschlossene Sache war. Wer \"Mein Kampf\" gelesen hat konnte sich im Grunde keine Ausreden für seit Jahren geplante Dinge mehr suchen und hätte wissen müssen dass das ganze Schritt für Schritt geplant war und verschiedene Phasen durchlaufen musste um sein volles Grauen zu entfachen 😓",
    "owner": {
      "id": "XmLA_lGkLjjeyCozniJhEg==",
      "username": "jLfi7DyiFzx7NZ8_xOFD5w=="
    },
    "likes_count": 7,
    "answers": []
  },
  {
    "id": 17994575809391143,
    "created_at": 1636484133,
    "text": "Dafür gibt es keine Worte... 😢",
    "owner": {
      "id": "9GxlqRknyZr-w-FjN5_Dhg==",
      "username": "C6HNF3Ar7k3mBpC5Z5C41w=="
    },
    "likes_count": 3,
    "answers": []
  },
  {
    "id": 18191482390122841,
    "created_at": 1636484036,
    "text": "😢😢😢😢",
    "owner": {
      "id": "4y4vSWLt2Ll1-w9nplMqww==",
      "username": "zbwIFUr5J2tq9do481QTEg=="
    },
    "likes_count": 1,
    "answers": []
  },
  {
    "id": 17915851691082193,
    "created_at": 1636483937,
    "text": "Unsere Synagoge in Krumbach brannte erst am 26.11.1939 nieder 😢 .... jedoch wurden bereits in der Progromnacht jüdische Gemeindemitglieder gezwungen die Synagoge zu räumen, damit die Synagoge als Heulager für die Wehrmacht genutzt werden konnte.... unsere Geschichte ist einfach grauenvoll und es sollte dagegen gewirkt werden, dass solch ein Verlauf nochmals geschieht #teamsoffer",
    "owner": {
      "id": "lKGVXJ5WkD4h90x6A64jdg==",
      "username": "2KqiuclfkmhQMYpF9q4Yxw=="
    },
    "likes_count": 3,
    "answers": [
      {
        "id": 18258784063048083,
        "created_at": 1636486160,
        "text": "@2KqiuclfkmhQMYpF9q4Yxw== Das Krumbach im Landkreis GZ? (frag nur weil ich nicht sicher weiß, ob es nicht noch andere Krumbachs gibt 😅)",
        "owner": {
          "id": "WCvKFQOJZ9Nps46QU5naiw==",
          "username": "Fy-DLa3DTwl8nhY6R4Sr0A=="
        },
        "likes_count": 2
      },
      {
        "id": 18005209576367851,
        "created_at": 1636537274,
        "text": "@2KqiuclfkmhQMYpF9q4Yxw== danke für die Antwort! Bin aus aus dem Nachbarlandkreis und bei den kleinen Dörfern ist oft nur schwer was rauszufinden über die Zeit (liegt wahrscheinlich auch daran, dass meine Eltern zugezogen sind und innerfamiliär keine Geschichten weitergetragen wurden). Aber ich find‘s immer wichtig so Geschichten zu kennen, wo man auch lokal n Bezug dazu hat. Danke Dir für‘s erzählen!",
        "owner": {
          "id": "WCvKFQOJZ9Nps46QU5naiw==",
          "username": "Fy-DLa3DTwl8nhY6R4Sr0A=="
        },
        "likes_count": 1
      },
      {
        "id": 17939580439680290,
        "created_at": 1636527454,
        "text": "@AEnUymL0-C3D-6VwXS3GYw== ja genau 😊 Krumbach, Schwaben im LK GZ 😊",
        "owner": {
          "id": "lKGVXJ5WkD4h90x6A64jdg==",
          "username": "2KqiuclfkmhQMYpF9q4Yxw=="
        },
        "likes_count": 1
      },
      {
        "id": 17906089646138249,
        "created_at": 1636579243,
        "text": "@2KqiuclfkmhQMYpF9q4Yxw== danke für die Infos! Da versuch ich mal drauf zu achten, wenn ich‘s nächste Mal in Krumbach bin.",
        "owner": {
          "id": "WCvKFQOJZ9Nps46QU5naiw==",
          "username": "Fy-DLa3DTwl8nhY6R4Sr0A=="
        },
        "likes_count": 1
      },
      {
        "id": 17856783899649702,
        "created_at": 1636575380,
        "text": "@AEnUymL0-C3D-6VwXS3GYw==  das freut mich. In Krumbach haben wir ein Mahnmal für unsere ehemalige Synagoge, was ich super finde. Auch die Stadtschilder unseres jüdischen Ortsteils \"Hürben\" hängen noch. Und somit haben wir immer noch die Geschichte in unserem Alltag und die Kinder wachsen heute noch damit auf.... diese Zeit darf nicht vergessen werden. Unser jüdischer Friedhof musste leider wegen Vandalismus gesperrt werden und darf nur noch unter Aufsicht besucht werden. Absolut erbärmlicher Zustand. Da frägt man sich ernsthaft, was solche Menschen im Kopf haben 😢",
        "owner": {
          "id": "lKGVXJ5WkD4h90x6A64jdg==",
          "username": "2KqiuclfkmhQMYpF9q4Yxw=="
        },
        "likes_count": 1
      }
    ]
  },
  {
    "id": 17968288966475415,
    "created_at": 1636483859,
    "text": "😔",
    "owner": {
      "id": "395euRknkbYzo5dwbu0lqw==",
      "username": "97_ZHd6B0yvtNCP6ifpZfQ=="
    },
    "likes_count": 1,
    "answers": []
  },
  {
    "id": 17903202086195755,
    "created_at": 1636483650,
    "text": "Unfassbar, dass diese „Rechte Gesinnung“ immer noch da ist und wieder mehr wird",
    "owner": {
      "id": "ayXXM02oGYVH8GX6wkoNCA==",
      "username": "6wG0uT1hcaPegOshk4ZUAQ=="
    },
    "likes_count": 7,
    "answers": []
  },
  {
    "id": 17910993860068462,
    "created_at": 1636483553,
    "text": "😢😢😢😢😢",
    "owner": {
      "id": "X0gIcLYg6aQj810vQPCteg==",
      "username": "lz45i-yIBDooH1h5DIJcdA=="
    },
    "likes_count": 3,
    "answers": []
  },
  {
    "id": 17910318089187023,
    "created_at": 1636483436,
    "text": "Und erst vor wenigen Monaten gab es hier in Ulm erneut einen Brandanschlag auf die Synagoge...",
    "owner": {
      "id": "j75C44SU19FcJqmDpfeipQ==",
      "username": "fNslfGcfyHwWMLNeoKy-UQ=="
    },
    "likes_count": 11,
    "answers": [
      {
        "id": 17979044596434847,
        "created_at": 1636485808,
        "text": "@wFb6wAmZd-KYW0F3U3NBiA== nicht ganz, die alte Synagoge wurde von den Nazis nach dem Brand leider abgerissen... Erst vor wenigen Jahren (2012!!!) wurde die neue Synagoge ganz in der Nähe der ehemaligen im Zentrum Ulms erbaut!",
        "owner": {
          "id": "j75C44SU19FcJqmDpfeipQ==",
          "username": "fNslfGcfyHwWMLNeoKy-UQ=="
        },
        "likes_count": 2
      },
      {
        "id": 17941189735637227,
        "created_at": 1636485657,
        "text": "@wFb6wAmZd-KYW0F3U3NBiA== Die Ulmer Synagoge sieht heute ganz anders aus als damals.",
        "owner": {
          "id": "7mgU_kvBU8xJl5cSAJJF9A==",
          "username": "AJtPUF9ejvDXwBdxY528Xg=="
        },
        "likes_count": 2
      },
      {
        "id": 17917243786954498,
        "created_at": 1636485506,
        "text": "@fNslfGcfyHwWMLNeoKy-UQ== ist das die gleiche Synagoge wie um 1940, sprich ist die Synagoge von damals wieder aufgebaut worden, so wie sie war?",
        "owner": {
          "id": "EkI6uu0s2xqKtwVoIdqhMg==",
          "username": "wFb6wAmZd-KYW0F3U3NBiA=="
        },
        "likes_count": 1
      },
      {
        "id": 17901132971349944,
        "created_at": 1636483852,
        "text": "@JH1UKyrLxUoBsKciatKXzw== ich kann mir kaum vorstellen was sich die jüdische Gemeinde Ulms gedacht haben muss! Es war echt schockierend sowas heute passieren zu sehen",
        "owner": {
          "id": "j75C44SU19FcJqmDpfeipQ==",
          "username": "fNslfGcfyHwWMLNeoKy-UQ=="
        },
        "likes_count": 5
      },
      {
        "id": 17897614694501654,
        "created_at": 1636486759,
        "text": "@fNslfGcfyHwWMLNeoKy-UQ== danke, dann schau ich mir die mal an, wenns geht",
        "owner": {
          "id": "EkI6uu0s2xqKtwVoIdqhMg==",
          "username": "wFb6wAmZd-KYW0F3U3NBiA=="
        },
        "likes_count": 2
      },
      {
        "id": 17870274056613798,
        "created_at": 1636484287,
        "text": "@fNslfGcfyHwWMLNeoKy-UQ== unglaublich aber wahr man sehe die Aktuellen Narichten bzw frage die letzten Zeitweilig lebenden Die noch von 1942 geborenen übrig sind da haben die Senioren berichtet mit den Worten ja genau so fing es damals an als das mit dem Krieg begang letzte Woche hatte meine Azubiklasse einen Vortrag zugehört von einem Syrischen Jungen der aus dem Krieg flüchtete 👀",
        "owner": {
          "id": "42HLJWGU79OAxZJd0cjomA==",
          "username": "3pYbwLAQ0fLSLHWqNTZIHw=="
        },
        "likes_count": 2
      },
      {
        "id": 17848562444658555,
        "created_at": 1636483717,
        "text": "@fNslfGcfyHwWMLNeoKy-UQ== das ist heftig😢 ich hoffe intzwischen das sich die Vergangenheit nicht weiter Wiederholt",
        "owner": {
          "id": "42HLJWGU79OAxZJd0cjomA==",
          "username": "3pYbwLAQ0fLSLHWqNTZIHw=="
        },
        "likes_count": 3
      }
    ]
  },
  {
    "id": 17930181817740117,
    "created_at": 1636483407,
    "text": "So etwas darf nie wieder passieren. 😢",
    "owner": {
      "id": "0-zrNn0VLze7KvJLUKpfVQ==",
      "username": "tRp-RgJRC2yvYU3Iex1nqw=="
    },
    "likes_count": 8,
    "answers": [
      {
        "id": 18194578834191655,
        "created_at": 1636489663,
        "text": "@wZA9-JowIVlgfK1FslhIQg== ich weiß und es ist schrecklich. Aber dort haben wir persönlich keinen Einfluss,  höchstens unsere Politiker.  Hier in Deutschland sind wir alle dafür zuständig aufzupassen,  dass so etwas nie wieder passiert.",
        "owner": {
          "id": "0-zrNn0VLze7KvJLUKpfVQ==",
          "username": "tRp-RgJRC2yvYU3Iex1nqw=="
        },
        "likes_count": 2
      },
      {
        "id": 18153438715173907,
        "created_at": 1636620707,
        "text": "@QC1Z7LpiYihPHCZObuIQhA== nee so genau kenne ich mich nicht aus mit der Geschichte das ich genau weiß wie das angefangen hat.  Vielleicht kannst du weiterhelfen? Das ist aber auch gar nicht mein Punkt. Ich denke ja nicht das es heute ein Einzelfall ist. Ich denke nur das es zwei verschiedene Probleme sind. Das eine ist die problematische Tendenz zur diskrimination der Menschheit im allgemeinen (wenn man das als Beginn des Nationalsozialismus sieht dann hat er wohl am Beginn der Menschheit angefangen) und das andere ist eine systematische Diskriminier seitens des Gesetzes, ausgeführt durch die Executive. Ich bin dankbar das es heute zumindest hier in unserer Rechtsgebung immer ein Verbrechen ist Menschen physisches Leid zuzufügen.",
        "owner": {
          "id": "4Ec8xbRrqcqpEXJ3zI5hbA==",
          "username": "wZA9-JowIVlgfK1FslhIQg=="
        },
        "likes_count": 0
      },
      {
        "id": 18020720434336554,
        "created_at": 1636487193,
        "text": "So etwas passier noch heute jeden Tag. In muslimischen Ländern an Juden und Christen und in China an Muslimen, Christen..",
        "owner": {
          "id": "4Ec8xbRrqcqpEXJ3zI5hbA==",
          "username": "wZA9-JowIVlgfK1FslhIQg=="
        },
        "likes_count": 3
      },
      {
        "id": 17931645166734353,
        "created_at": 1636525910,
        "text": "@wZA9-JowIVlgfK1FslhIQg== In Deutschland passiert das auch. Gewalt gegen Jüd*Innen, gegen jüdische Einrichtungen und Synagogen (Ulm, Halle). Auch hier gibt es antisemitische Gewalt. Und sehr viele gefährliche antisemitische Vorurteile. Und auch in der christlichen, christlich geprägten, Weißen Mehrheitsgesellschaft",
        "owner": {
          "id": "M-PYqAZdrra_mvQ2aBZ2lQ==",
          "username": "IKomZ8Py4JqAR0NLUa-dBw=="
        },
        "likes_count": 8
      },
      {
        "id": 17926307104906897,
        "created_at": 1636610561,
        "text": "@wZA9-JowIVlgfK1FslhIQg== und genau da fängt das Problem an. Du stempelst alles als Einzelfall ab. Was glaubst du, wie es damals angefangen hat?",
        "owner": {
          "id": "E0R-9vBPDF-nz4YLj3PEeA==",
          "username": "QC1Z7LpiYihPHCZObuIQhA=="
        },
        "likes_count": 0
      },
      {
        "id": 17922371836963093,
        "created_at": 1636672297,
        "text": "@wZA9-JowIVlgfK1FslhIQg== Damit verharmlost du jedoch den Holocaust.",
        "owner": {
          "id": "4Ko8vbOLC9g6FCrEKGtRbw==",
          "username": "H7KmzuTymVSSnFVg4fW_Aw=="
        },
        "likes_count": 0
      },
      {
        "id": 17907149477254665,
        "created_at": 1637072815,
        "text": "@H7KmzuTymVSSnFVg4fW_Aw== das ist nicht meine Ansicht. Welche meiner Aussagen meinst du genau?",
        "owner": {
          "id": "4Ec8xbRrqcqpEXJ3zI5hbA==",
          "username": "wZA9-JowIVlgfK1FslhIQg=="
        },
        "likes_count": 0
      },
      {
        "id": 17906032718142172,
        "created_at": 1636583760,
        "text": "@H7KmzuTymVSSnFVg4fW_Aw== Mh ich denke nicht dass man das so direkt sagen kann... Menschenverachtende Taten und Einstellungen einzelner Personen oder selbst Personengruppen ( wie furchtbar sie auch sein mögen) sind etwas anderes als systematisch geplante vernichtung oder „Umerziehung“ von Seiten der Regierung.",
        "owner": {
          "id": "4Ec8xbRrqcqpEXJ3zI5hbA==",
          "username": "wZA9-JowIVlgfK1FslhIQg=="
        },
        "likes_count": 0
      },
      {
        "id": 17862818183604054,
        "created_at": 1636500712,
        "text": "@wZA9-JowIVlgfK1FslhIQg== So etwas passiert auch in Deutschland jeden Tag - wieder an Juden.",
        "owner": {
          "id": "4Ko8vbOLC9g6FCrEKGtRbw==",
          "username": "H7KmzuTymVSSnFVg4fW_Aw=="
        },
        "likes_count": 4
      }
    ]
  },
  {
    "id": 17952916432552973,
    "created_at": 1636483390,
    "text": "Diese schreckliche Zeit, darf sich niemals wiederholen!!",
    "owner": {
      "id": "TDyJzXAewGUfmkXqRqH3Cg==",
      "username": "iC_963RHjPAZCaYyLXUhbA=="
    },
    "likes_count": 5,
    "answers": []
  },
  {
    "id": 17950651735565296,
    "created_at": 1636483215,
    "text": "🕯️",
    "owner": {
      "id": "RebxTNCF2huRJ0RO9TvKZw==",
      "username": "U5r3K0nTJyD5Wjyv2IGtrw=="
    },
    "likes_count": 4,
    "answers": []
  },
  {
    "id": 17918841263030723,
    "created_at": 1636483187,
    "text": "Ist diese Synagoge in der Nähe deines Hauses?",
    "owner": {
      "id": "aH1jirnWPEj0OCpwGwynkQ==",
      "username": "xyvvZ3-0EvPKjvgMciLwPQ=="
    },
    "likes_count": 0,
    "answers": [
      {
        "id": 17933497543782909,
        "created_at": 1636501944,
        "text": "@hib4mKmHA-vgwtwb0Q_04A== Ich bin in einer Kleinstadt im Sauerland aufgewachsen. In unserer Nähe gibt es heute eine Synagogengasse. Ich gehe / fahre oft daran vorbei. 🙏 für alle, die in Vergangenheit und Zukunft unter Verfolgung leiden!",
        "owner": {
          "id": "W2WjfnB-fuvAmVldKFobHA==",
          "username": "PHzf68YhoOfgIkPlfUV6Zg=="
        },
        "likes_count": 2
      },
      {
        "id": 17926473274821072,
        "created_at": 1636486005,
        "text": "@xyvvZ3-0EvPKjvgMciLwPQ== Vor vier Jahren stand sie dort noch und es wären fünf Minuten zu Fuß dahin gewesen.",
        "owner": {
          "id": "9rICyTfoSV8xPafAZ0Xo0w==",
          "username": "hib4mKmHA-vgwtwb0Q_04A=="
        },
        "likes_count": 11
      }
    ]
  },
  {
    "id": 17999437342359485,
    "created_at": 1636483178,
    "text": "Habe heute meine Seminararbeit über den neunten November abgegeben!",
    "owner": {
      "id": "mzrUopFDXfItxnHUhLyAyQ==",
      "username": "9EZ8xMcDnxkuwTNVX_9tiQ=="
    },
    "likes_count": 20,
    "answers": []
  },
  {
    "id": 17976862831415466,
    "created_at": 1636483100,
    "text": "So grausam und unmenschlich😢 Auch heute muss man aufpassen weil die \"rechte\"Seite wieder enormen Zulauf bekommt. Währet den Anfängen- Nie wieder - nie wieder !!!!",
    "owner": {
      "id": "BcgguufgEgv053w4ZXrfhw==",
      "username": "LBKoi2V3WAbSB7KsraQ-HQ=="
    },
    "likes_count": 36,
    "answers": [
      {
        "id": 17983266358419020,
        "created_at": 1636484434,
        "text": "Und aktuell sitzen wieder Menschen auf der Flucht zwischen Polen und Belarus (Weißrussland) fest.",
        "owner": {
          "id": "77suPV_hajbMBzrjc4ICwA==",
          "username": "_Xnkadok_plwOGxAVUs85g=="
        },
        "likes_count": 4
      },
      {
        "id": 17882316026499243,
        "created_at": 1636500664,
        "text": "@_Xnkadok_plwOGxAVUs85g== Das, was diesen Menschen wiederfährt ist schrecklich. Und trotzdem nicht mit dem Holocaust vergleichbar. Das Ziel des NS- Regimes war die Vernichtung/Ausrottung aller Juden.",
        "owner": {
          "id": "4Ko8vbOLC9g6FCrEKGtRbw==",
          "username": "H7KmzuTymVSSnFVg4fW_Aw=="
        },
        "likes_count": 1
      }
    ]
  },
  {
    "id": 17971995907460055,
    "created_at": 1636483086,
    "text": "Wusste man eigentlich zu der Zeit des Überfalls auf Polen (bzw. Wie es im Text heißt 1 Jahr danach), dass Deutschland den Kriegsbeginn verursacht hat? Oder waren alle Medien da bereits gleichgeschalten? Ich weiß, ich könnte es auch selber nachschauen, vielleicht antwortet aber eine nette Seele^^",
    "owner": {
      "id": "PPxFSc2fyaHsjnuej3fviA==",
      "username": "bKcHg_Qy3OwrtnyWQuUlWg=="
    },
    "likes_count": 2,
    "answers": [
      {
        "id": 17991453715404284,
        "created_at": 1636484616,
        "text": "@AEnUymL0-C3D-6VwXS3GYw== eine nette Seele hat sich für eine Erklärung gefunden ❤️ ich danke vielmals!",
        "owner": {
          "id": "PPxFSc2fyaHsjnuej3fviA==",
          "username": "bKcHg_Qy3OwrtnyWQuUlWg=="
        },
        "likes_count": 1
      },
      {
        "id": 17975352391444296,
        "created_at": 1636484402,
        "text": "@bKcHg_Qy3OwrtnyWQuUlWg== @raphael.deinbesteralbtraum Das \"Schriftleitergesetz\", trat bereits zum 01. Januar 1934 in Kraft. Es war der erste Schritt zur Kontrolle der Presse/Journalisten. Die Presse war längst gleichgeschaltet. Bei der bpb habe ich neulich eine interessantes pdf gefunden, in dem z. B. - passend zu heute - die Presseanweisungen für den 9. November 1938 bzw. auch davor und danach nachgelesen werden können. Viele wussten aber dennoch, dass Deutschland den Krieg begonnen hat. Sei es weil sie den PropagandaSprech durchblickten, Kontakte ins Ausland hatten, \"Feindsender\" hörten...",
        "owner": {
          "id": "WCvKFQOJZ9Nps46QU5naiw==",
          "username": "Fy-DLa3DTwl8nhY6R4Sr0A=="
        },
        "likes_count": 8
      },
      {
        "id": 17914902137105251,
        "created_at": 1636483999,
        "text": "@bKcHg_Qy3OwrtnyWQuUlWg== Der Krieg gegen Polen wurde mit einem von der SA oder SS inszenierten Überfall auf einen grenznahen Radiosender gerechtfertigt. In der drauffolgenden Rede früh im Reichstag wurde es so aussehen gelassen, als hätte Polen den Überfall begonnen. Daher stammt auch die Recht bekannte Zeile: \"Seit 5:45 wird jetzt zurückgeschossen, ab jetzt wird Bombe mit Bombe vergolten\". Selbst das war eine Lüge, denn der Beschuss auf die polnische Küste von deutschen Schiffen begann schon eine Stunde früher. Wie genau jetzt die Medien dazu berichteten, weiß ich auch nicht, ich denke aber mal dass die Herausgeber der größten Zeitungen und Radiosendungen die Meldungen der Regierung und Armeeführung nutzen und die waren natürlich alle schon gebrieft.",
        "owner": {
          "id": "HDAAkIuZ-Y4vXA02BhVncg==",
          "username": "fF5JDz4JauncK-nliHndXw=="
        },
        "likes_count": 6
      }
    ]
  },
  {
    "id": 18175045042090411,
    "created_at": 1636483010,
    "text": "Auf @stolpersteineulm werden Familien aus Ulm vorgestellt, die betroffen waren. Mehr Familiengeschichten auch unter @stolpersteine",
    "owner": {
      "id": "WCvKFQOJZ9Nps46QU5naiw==",
      "username": "Fy-DLa3DTwl8nhY6R4Sr0A=="
    },
    "likes_count": 21,
    "answers": []
  },
  {
    "id": 17922651937952586,
    "created_at": 1636482934,
    "text": "Der Synagogenbrand fand 1938 statt, mithin vor drei und nicht vor vier Jahren, wie Sophie Scholl hier in den Mund gelegt wird.",
    "owner": {
      "id": "JgfdusfH1kPJl3YmpjHGUg==",
      "username": "AV0WM66-FO6CoNIhGtc5yQ=="
    },
    "likes_count": 2,
    "answers": [
      {
        "id": 18260101759048391,
        "created_at": 1636483264,
        "text": "@rb0P5Ns40PAN156DU71Wmg== oh, dann habe wohl ich nicht aufgepasst...",
        "owner": {
          "id": "JgfdusfH1kPJl3YmpjHGUg==",
          "username": "AV0WM66-FO6CoNIhGtc5yQ=="
        },
        "likes_count": 3
      },
      {
        "id": 17939120824723656,
        "created_at": 1636483171,
        "text": "@AV0WM66-FO6CoNIhGtc5yQ== aber es ist doch 1942 hier, passt doch? Oder steh ich auch auf‘m Schlauch.",
        "owner": {
          "id": "WCvKFQOJZ9Nps46QU5naiw==",
          "username": "Fy-DLa3DTwl8nhY6R4Sr0A=="
        },
        "likes_count": 4
      },
      {
        "id": 17939060461665664,
        "created_at": 1636483501,
        "text": "@hib4mKmHA-vgwtwb0Q_04A== Ist schon klar, zwei weitere Teilnehmer haben mich schon darauf aufmerksam gemacht. Vielen Dank!",
        "owner": {
          "id": "JgfdusfH1kPJl3YmpjHGUg==",
          "username": "AV0WM66-FO6CoNIhGtc5yQ=="
        },
        "likes_count": 3
      },
      {
        "id": 17938594354724639,
        "created_at": 1636483316,
        "text": "@AEnUymL0-C3D-6VwXS3GYw== mea  culpa, wenn wir uns schon im Jahr 1942 befinden.",
        "owner": {
          "id": "JgfdusfH1kPJl3YmpjHGUg==",
          "username": "AV0WM66-FO6CoNIhGtc5yQ=="
        },
        "likes_count": 2
      },
      {
        "id": 17895334631455083,
        "created_at": 1636483181,
        "text": "@AV0WM66-FO6CoNIhGtc5yQ== wir befinden uns im Jahr 1942, also ist vier Jahre korrekt",
        "owner": {
          "id": "ZcH5QZ4itQ4_clsRFa3axw==",
          "username": "rb0P5Ns40PAN156DU71Wmg=="
        },
        "likes_count": 3
      },
      {
        "id": 17884626059484297,
        "created_at": 1636483421,
        "text": "@AV0WM66-FO6CoNIhGtc5yQ== #TeamSoffer In der Erzählung schreiben wir das Jahr 1942. Der Synagogenbrand fand aus Sophies Perspektive demnach vor vier Jahren statt.",
        "owner": {
          "id": "9rICyTfoSV8xPafAZ0Xo0w==",
          "username": "hib4mKmHA-vgwtwb0Q_04A=="
        },
        "likes_count": 21
      }
    ]
  },
  {
    "id": 17934386197748415,
    "created_at": 1636482757,
    "text": "Es darf niemals wieder passieren.",
    "owner": {
      "id": "OkAJNUURFYxKx2dHssfW2A==",
      "username": "Ri1EEWNMJecvKsVQr3OGPw=="
    },
    "likes_count": 134,
    "answers": [
      {
        "id": 18261898552028529,
        "created_at": 1636484855,
        "text": "@Ri1EEWNMJecvKsVQr3OGPw== Wir müssen unbedingt diese Erinnerung wachhalten.",
        "owner": {
          "id": "9rICyTfoSV8xPafAZ0Xo0w==",
          "username": "hib4mKmHA-vgwtwb0Q_04A=="
        },
        "likes_count": 63
      },
      {
        "id": 17943707038584170,
        "created_at": 1636535171,
        "text": "@hib4mKmHA-vgwtwb0Q_04A== Tatsächlich habe ich den Tag gestern genutzt,  um meine Eltern zum 9.11.38 zu befragen.  Sie waren damals 5 Jahre alt. Aber die zerstörten , sehr beliebten jüdischen Geschäfte,  zB Kaufhaus Uhlfelder in München,  die davor postierten, aggressiven SA-Schlägertrupps haben sogar die beiden als Kinder geschockt.  Mein Vater erzählt,  er könne sich nicht mehr erinnern,  wie er mit meinem Großvater in die Stadt gekommen sei. Was gesprochen wurde.  Aber dieses Bild hat sich eingebrannt zusammen mit einem Gefühl von Trauer und ohnmächtiger Wut.",
        "owner": {
          "id": "CATLVjpITboZENFX8P-v7A==",
          "username": "jv4uq0dsiHc3qV9Owgx0jw=="
        },
        "likes_count": 3
      },
      {
        "id": 17937359134692745,
        "created_at": 1636525484,
        "text": "@hib4mKmHA-vgwtwb0Q_04A== .....\"Erinnerung wachhalten\"....ist zu schwach. Das ist nur eine Floskel. Diese Formulierung ist gefährlich. Sie beruhigt nur die sich erinnernde Mehrheitsgesellschaft. @hib4mKmHA-vgwtwb0Q_04A== ihr habt doch einen Bildungsauftrag, oder? Ihr wollt doch was bewegen, oder? Wir müssen aus der bloßen Erinnerungskultur raus.  Gewalt gegen Jüd*Innen und Anschläge auf jüdische Einrichtungen passieren so oft (jetzt wird auch manchmal in Medien drüber berichtet.) Folgt jüdischen Aktivist*Innen. Solidaridiert euch mit Ihnen. Lernt von ihnen. Hört ihre Podcasts. Lest ihre Bücher. Informiert dann selbst über Antisemitismus, sprecht ihn an. Duldet ihn nicht.",
        "owner": {
          "id": "M-PYqAZdrra_mvQ2aBZ2lQ==",
          "username": "IKomZ8Py4JqAR0NLUa-dBw=="
        },
        "likes_count": 5
      },
      {
        "id": 17907174941277606,
        "created_at": 1636500402,
        "text": "@Ri1EEWNMJecvKsVQr3OGPw== Es passiert aber wieder - und viele wollen es nicht wahrhaben, schweigen oder sehen weg. #neveragainisnow",
        "owner": {
          "id": "4Ko8vbOLC9g6FCrEKGtRbw==",
          "username": "H7KmzuTymVSSnFVg4fW_Aw=="
        },
        "likes_count": 8
      }
    ]
  },
  {
    "id": 17934653632752664,
    "created_at": 1636482717,
    "text": "Das diese Worte mal Realität waren...Es ist einfach unbegreiflich, unfassbar und so unsäglich schrecklich.",
    "owner": {
      "id": "FQ_pD0aGcuxLdFcZevUaVg==",
      "username": "l88uv4bnD-0sBUvSe_yD6A=="
    },
    "likes_count": 11,
    "answers": []
  },
  {
    "id": 17888958482407457,
    "created_at": 1636482710,
    "text": "😢 So grausam",
    "owner": {
      "id": "te0skmfhjuzEEODHrePjNg==",
      "username": "ML76PwKuRj4z5Q4VNQvs6Q=="
    },
    "likes_count": 4,
    "answers": []
  },
  {
    "id": 17916886957971720,
    "created_at": 1636482647,
    "text": "#TeamSoffer In der Nacht vom 9. auf den 10. November fanden in Deutschland staatlich organisierte Pogrome gegen die jüdische Bevölkerung statt. Die heutige Bezeichnung dafür ist Reichspogromnacht. Pogrom bedeutet Ausschreitungen gegen nationale, religiöse oder ethnische Minderheiten. Zeitzeugenberichte finden sich auf Youtube beim Zeitzeugen-Portal unter dem Stichwort \"1938: Die Pogromnacht – 9. November\".\n\nOrganisiert wurden die Pogrome von den Nationalsozialisten, die als Vorwand das Attentat auf einen deutschen Diplomaten in Paris durch einen polnischen Juden nutzten. Dieser hatte darauf aufmerksam machen wollen, dass durch deutsche Politik Tausende polnische Jüdinnen und Juden im Grenzland zwischen Deutschland und Polen ohne jegliche Versorgung festsaßen und in keines der Länder einreisen durften. Darunter waren auch die Eltern des Attentäters.\n\nAm 9. November hielt Goebbels eine Hetzrede, Trupps von SA und SS begannen in jener Nacht sogenannte “Aktionen” durchzuführen. Deutsche Bürger:innen beteiligten sich an den Pogromen, sahen weg, sehr wenige halfen Verfolgten. Hier zeigte sich, wie sehr Antisemitismus in der deutschen Bevölkerung verbreitet war. \nAls sogenannte “Sühneleistung” für die Sachschäden mussten deutsche Jüdinnen und Juden eine Milliarde Reichsmark Strafe zahlen.\n\nCa. 1.300 jüdische Menschen starben während oder in Folge der Pogrome, die Hälfte aller Synagogen in Deutschland wurde beschädigt oder zerstört und am 10. November wurden mehr als 30.000 Juden (ausschließlich Männer) in Konzentrationslager verschleppt. Mehr Informationen zum Thema findet ihr bei der Bundeszentrale für Politische Bildung (bpb.de) oder beim Lebendigen Museum Online (dhm.de/lemo/) wenn ihr nach dem Datum \"9.11.1938\" sucht.",
    "owner": {
      "id": "9rICyTfoSV8xPafAZ0Xo0w==",
      "username": "hib4mKmHA-vgwtwb0Q_04A=="
    },
    "likes_count": 402,
    "answers": [
      {
        "id": 18213488707101360,
        "created_at": 1636541928,
        "text": "@YCEFJFmB8LFJGGZMoZiLDg== ach, stimmt. Du hast recht. Tut mir leid. Habe ich wohl vergessen. 🙇🏼‍♀️🙇🏼‍♀️😅",
        "owner": {
          "id": "fWGgLgl5SRppcDt-rN8rIA==",
          "username": "gARteX-ZtUAd2Pjhle5jzg=="
        },
        "likes_count": 0
      },
      {
        "id": 18204165463114786,
        "created_at": 1636490085,
        "text": "@hib4mKmHA-vgwtwb0Q_04A== danke",
        "owner": {
          "id": "T3FIdr5_bY5CPSZcMyX_zA==",
          "username": "xZJnsJaegQB46g9zCSPQDA=="
        },
        "likes_count": 0
      },
      {
        "id": 18169324681166657,
        "created_at": 1636483021,
        "text": "@hib4mKmHA-vgwtwb0Q_04A== danke für so viel Aufklärung ❤️",
        "owner": {
          "id": "0g9IaffWkgqU5xT0EDQgBg==",
          "username": "GpBoHuQeNBTDE8l3WOtejg=="
        },
        "likes_count": 12
      },
      {
        "id": 17980784875425824,
        "created_at": 1636529967,
        "text": "@fY07_Ewtn_xET77KBwcM8g== Jahre aus Seide, Jahre aus Glas, der dritte Name fällt mir leider nicht ein.",
        "owner": {
          "id": "fWGgLgl5SRppcDt-rN8rIA==",
          "username": "gARteX-ZtUAd2Pjhle5jzg=="
        },
        "likes_count": 2
      },
      {
        "id": 17953143217554829,
        "created_at": 1636542098,
        "text": "@gARteX-ZtUAd2Pjhle5jzg== kein Problem, freu mich auf jeden Fall auf diese Serie. Werde ich bestellen, halt nicht bei Amazon. Danke.",
        "owner": {
          "id": "J5Ngq2vRUyKCfXhdKRSvBA==",
          "username": "YCEFJFmB8LFJGGZMoZiLDg=="
        },
        "likes_count": 2
      },
      {
        "id": 17951763010520485,
        "created_at": 1636489806,
        "text": "@xZJnsJaegQB46g9zCSPQDA== als Vorwand für die Novemberpogrome nutzten die Nationalsozialisten das Attentat auf den deutschen Diplomaten Ernst Eduard von Rath, der am 7. November 1938  von einem polnischen Staatsbürger jüdischen Glaubens attackiert wurde. Anschließend wurde eine Zahlung von 1.000.000 Reichsmark als „Sühneleistung“ aufgrund der „feindlichen Haltung des Judentums gegenüber dem deutschen Volk“ erlassen. Der Name passte damals gut ins Narrativ der Nationalisozialisten. Hoffe, ich konnte es erklären.",
        "owner": {
          "id": "-1ZkdUYb9a3qYhWgr5Ak-g==",
          "username": "ZI2VJ3WrTADEjx8-URf1sA=="
        },
        "likes_count": 6
      },
      {
        "id": 17916256634080869,
        "created_at": 1636524723,
        "text": "@hib4mKmHA-vgwtwb0Q_04A== ich habe letztes Jahr ein Buch darüber gelesen. Bzw drei. Es wurden alte Tagebücher gefunden, von einer Ruth Meyer und die wurden in einen Roman umgewandelt, die Autorin schreibt am Ende des Buches genau was sie dazu gedacht hat. Damit man weiß wie viel wahr ist und was eben nicht. Meistens sind es aber nur kleine Nebenrollen die sie sich dazu gedacht hat, einfach nur damit es eben ein Roman wird. Die Tagebücher sind heute ausgestellt in Krefeld in der Merländervilla wenn ich mich nicht täusche. Wer gerne liest, die Bücher sind sehr zu Empfehlen! Denn die Ruth hat die Flucht und alles andere wirklich sehr gut beschrieben",
        "owner": {
          "id": "fWGgLgl5SRppcDt-rN8rIA==",
          "username": "gARteX-ZtUAd2Pjhle5jzg=="
        },
        "likes_count": 3
      },
      {
        "id": 17908547936280067,
        "created_at": 1636532862,
        "text": "@gARteX-ZtUAd2Pjhle5jzg== Dankeschön 😊",
        "owner": {
          "id": "BLs_NRbl3DJ3dq7sFAw7Qw==",
          "username": "5CQIgI_eZYy6e6O1Yz7Ayg=="
        },
        "likes_count": 1
      },
      {
        "id": 17902274537208756,
        "created_at": 1636541764,
        "text": "@gARteX-ZtUAd2Pjhle5jzg== ich habe jetzt ein bisschen gegoogelt. Es gibt, laut Amazon sogar 4 Bücher. Danke für den Tipp",
        "owner": {
          "id": "J5Ngq2vRUyKCfXhdKRSvBA==",
          "username": "YCEFJFmB8LFJGGZMoZiLDg=="
        },
        "likes_count": 0
      },
      {
        "id": 17899554824372936,
        "created_at": 1636529762,
        "text": "@gARteX-ZtUAd2Pjhle5jzg== Weißt du noch wie die Bücher hießen oder die Autorin?",
        "owner": {
          "id": "BLs_NRbl3DJ3dq7sFAw7Qw==",
          "username": "5CQIgI_eZYy6e6O1Yz7Ayg=="
        },
        "likes_count": 1
      },
      {
        "id": 17898486758289023,
        "created_at": 1636484015,
        "text": "@hib4mKmHA-vgwtwb0Q_04A== die Synagoge in unserem Ort wurde damals nur nicht zerstört, weil sie nicht mehr jüdisch genutzt wurde, sondern als normales Wohnhaus von nicht-jüdischen bewohnt wurde.",
        "owner": {
          "id": "sIcpzS4OyUztNi_luGiJJQ==",
          "username": "P94AdPQgmCX3wXSVn48l0w=="
        },
        "likes_count": 3
      },
      {
        "id": 17886395690525771,
        "created_at": 1636489808,
        "text": "@xZJnsJaegQB46g9zCSPQDA== #TeamSoffer Die Sühneleistung auch \"Judenvermögensabgabe\" genannt war eine willkürliche Sonderabgabe die deutsche Juden für die \"feindliche Haltung gegenüber dem deutschen Volk\" leisten mussten. \"Der Terror der Pogromnacht wurde fortgesetzt durch Verordnungen, die den Juden auferlegten, eine \"Sühneleistung\" für die in Höhe von eine Milliarde Mark an das Deutsche Reich zu zahlen, alle Schäden sofort selbst zu beheben, die Kosten für die Wiederherstellung selbst aufzubringen und die von den Versicherungen gezahlten Entschädigungen an das Reich abzuführen.\" Mehr Informationen gibt es unter https://m.bpb.de/politik/hintergrund-aktuell/68670/9-november-1938-08-11-2011",
        "owner": {
          "id": "9rICyTfoSV8xPafAZ0Xo0w==",
          "username": "hib4mKmHA-vgwtwb0Q_04A=="
        },
        "likes_count": 20
      },
      {
        "id": 17875074308599307,
        "created_at": 1636490108,
        "text": "@LoH4i3Le_qbedXDw9ALNzQ== danke",
        "owner": {
          "id": "T3FIdr5_bY5CPSZcMyX_zA==",
          "username": "xZJnsJaegQB46g9zCSPQDA=="
        },
        "likes_count": 0
      },
      {
        "id": 17857167347647845,
        "created_at": 1636486987,
        "text": "@hib4mKmHA-vgwtwb0Q_04A== was bedeutet denn sühneleistung?",
        "owner": {
          "id": "T3FIdr5_bY5CPSZcMyX_zA==",
          "username": "xZJnsJaegQB46g9zCSPQDA=="
        },
        "likes_count": 1
      }
    ]
  },
  {
    "id": 18015775531342845,
    "created_at": 1636482644,
    "text": "Unglaublich grausam. Mir fallen keine Worte ein, um das auszudrücken, wie schrecklich ich das finde.",
    "owner": {
      "id": "0JGy1vW9l58a9uf5oEdpLw==",
      "username": "kaLhFxgcO_vBDDvxpYIEDw=="
    },
    "likes_count": 54,
    "answers": [
      {
        "id": 17932991710805437,
        "created_at": 1636484876,
        "text": "@kaLhFxgcO_vBDDvxpYIEDw== Es lässt mich auch sprachlos zurück…",
        "owner": {
          "id": "9rICyTfoSV8xPafAZ0Xo0w==",
          "username": "hib4mKmHA-vgwtwb0Q_04A=="
        },
        "likes_count": 11
      }
    ]
  }
]